hrm/__init__.py
hrm/__main__.py
hrm/interpreter.py
hrmi/__init__.py
hrmi/__main__.py
hrmi/interpreter.py
hrm_py-0.1.1.dist-info/LICENSE
hrm_py-0.1.1.dist-info/METADATA
hrm_py-0.1.1.dist-info/WHEEL
hrm_py-0.1.1.dist-info/top_level.txt
hrm_py-0.1.1.dist-info/RECORD
