Metadata-Version: 2.1
Name: hrm-py
Version: 0.1.1
Summary: Human Resource Machine (HRM) Interpreter
Home-page: UNKNOWN
Author: Sigmanificient
Author-email: contact@yohannboniface.dev
License: MIT
Project-URL: Github repository, https://github.com/Sigmanificient/HRM-Interpreter
Keywords: hrm,interpreter,interpreted language,human,resource,machine
Platform: unix
Platform: linux
Platform: osx
Platform: windows
Classifier: Intended Audience :: Developers
Classifier: Topic :: Software Development :: Build Tools
Classifier: License :: OSI Approved :: MIT License
Classifier: Programming Language :: Python :: 3 :: Only
Classifier: Programming Language :: Python :: 3.8
Classifier: Programming Language :: Python :: 3.9
Classifier: Programming Language :: Python :: 3.10
Requires-Python: >=3.8
License-File: LICENSE
Provides-Extra: testing
Requires-Dist: pytest (>=6.2.5) ; extra == 'testing'
Requires-Dist: mypy (>=0.910) ; extra == 'testing'
